jupyterlab_chat_toy/__init__.py
jupyterlab_chat_toy/handlers.py
jupyterlab_chat_toy/labextension/package.json
jupyterlab_chat_toy/labextension/schemas/jupyterlab-chat-toy/package.json.orig
jupyterlab_chat_toy/labextension/static/509.7a172541042cd92e7d86.js
jupyterlab_chat_toy/labextension/static/665.36f0655285d6517f6bdb.js
jupyterlab_chat_toy/labextension/static/remoteEntry.5ddd6e98fc220e6ecbf5.js
jupyterlab_chat_toy/labextension/static/style.js
jupyterlab_chat_toy/labextension/static/third-party-licenses.json
jupyterlab_chat_toy-0.1.8.data/data/share/jupyter/labextensions/jupyterlab-chat-toy/package.json
jupyterlab_chat_toy-0.1.8.data/data/share/jupyter/labextensions/jupyterlab-chat-toy/schemas/jupyterlab-chat-toy/package.json.orig
jupyterlab_chat_toy-0.1.8.data/data/share/jupyter/labextensions/jupyterlab-chat-toy/static/509.7a172541042cd92e7d86.js
jupyterlab_chat_toy-0.1.8.data/data/share/jupyter/labextensions/jupyterlab-chat-toy/static/665.36f0655285d6517f6bdb.js
jupyterlab_chat_toy-0.1.8.data/data/share/jupyter/labextensions/jupyterlab-chat-toy/static/remoteEntry.5ddd6e98fc220e6ecbf5.js
jupyterlab_chat_toy-0.1.8.data/data/share/jupyter/labextensions/jupyterlab-chat-toy/static/style.js
jupyterlab_chat_toy-0.1.8.data/data/share/jupyter/labextensions/jupyterlab-chat-toy/static/third-party-licenses.json
jupyterlab_chat_toy-0.1.8.dist-info/METADATA
jupyterlab_chat_toy-0.1.8.dist-info/WHEEL
jupyterlab_chat_toy-0.1.8.dist-info/top_level.txt
jupyterlab_chat_toy-0.1.8.dist-info/RECORD
