Metadata-Version: 2.1
Name: jupyterlab-chat-toy
Version: 0.1.8
Summary: AI Chat Extension for JupyterLab
Home-page: UNKNOWN
Author: ChandlerFan
Author-email: 411342747@qq.com
License: UNKNOWN
Keywords: jupyter,jupyterlab,jupyterlab-extension,chat
Platform: UNKNOWN
Classifier: Framework :: Jupyter
Classifier: Framework :: Jupyter :: JupyterLab
Classifier: Programming Language :: Python :: 3
Classifier: Programming Language :: Python :: 3.6
Classifier: Programming Language :: Python :: 3.7
Classifier: Programming Language :: Python :: 3.8
Classifier: Programming Language :: Python :: 3.9
Classifier: Programming Language :: Python :: 3.10
Classifier: Programming Language :: Python :: 3.11
Classifier: License :: OSI Approved :: BSD License
Requires-Python: >=3.6
Requires-Dist: jupyterlab (<4,>=3.2.9)
